pgapi/__init__.py
pgapi/__main__.py
pgapi/cli.py
pgapi/db.py
pgapi/hookspecs.py
pgapi/plugins.py
pgapi/py.typed
pgapi/recipes.py
pgapi/utils.py
pgapi-0.0.1a1.dist-info/LICENSE
pgapi-0.0.1a1.dist-info/METADATA
pgapi-0.0.1a1.dist-info/WHEEL
pgapi-0.0.1a1.dist-info/entry_points.txt
pgapi-0.0.1a1.dist-info/top_level.txt
pgapi-0.0.1a1.dist-info/RECORD
